MANIFEST.in
setup.py
c/droidtools_ext4fsmodule.c
c/ext4_utils/allocate.c
c/ext4_utils/allocate.h
c/ext4_utils/backed_block.c
c/ext4_utils/backed_block.h
c/ext4_utils/contents.c
c/ext4_utils/contents.h
c/ext4_utils/ext4.h
c/ext4_utils/ext4_extents.h
c/ext4_utils/ext4_jbd2.h
c/ext4_utils/ext4_utils.c
c/ext4_utils/ext4_utils.h
c/ext4_utils/extent.c
c/ext4_utils/extent.h
c/ext4_utils/indirect.c
c/ext4_utils/indirect.h
c/ext4_utils/jbd2.h
c/ext4_utils/make_ext4fs.c
c/ext4_utils/make_ext4fs.h
c/ext4_utils/output_file.c
c/ext4_utils/output_file.h
c/ext4_utils/sha1.c
c/ext4_utils/sha1.h
c/ext4_utils/simg2img.c
c/ext4_utils/sparse_crc32.c
c/ext4_utils/sparse_crc32.h
c/ext4_utils/sparse_format.h
c/ext4_utils/uuid.c
c/ext4_utils/uuid.h
c/ext4_utils/private/android_filesystem_config.h
droidtools/__init__.py
droidtools/bootimg.py
droidtools/ext4fs_utils.py
droidtools/minicpio.py
droidtools/mkbootimg.py
droidtools/test_ext4fs_utils.py
droidtools/unlokibootimg.py
droidtools/unpackbootimg.py
droidtools.egg-info/PKG-INFO
droidtools.egg-info/SOURCES.txt
droidtools.egg-info/dependency_links.txt
droidtools.egg-info/top_level.txt